aedes/remote_sensing_utils.py
aedes-0.0.2.dist-info/LICENSE.txt
aedes-0.0.2.dist-info/METADATA
aedes-0.0.2.dist-info/WHEEL
aedes-0.0.2.dist-info/top_level.txt
aedes-0.0.2.dist-info/RECORD
