Metadata-Version: 2.1
Name: aedes
Version: 0.0.2
Summary: A package for PROJECT AEDES
Home-page: https://github.com/xmpuspus/aedes
Author: Xavier Puspus
Author-email: xavier.puspus@cirrolytix.com
License: UNKNOWN
Platform: UNKNOWN
Classifier: Programming Language :: Python :: 3
Classifier: License :: OSI Approved :: MIT License
Classifier: Operating System :: OS Independent
Requires-Python: >=3.8.5
License-File: LICENSE.txt
